mcp_calculator_kel/__init__.py
mcp_calculator_kel/__main__.py
mcp_calculator_kel/server.py
mcp_calculator_financeblue-0.1.0.dist-info/METADATA
mcp_calculator_financeblue-0.1.0.dist-info/WHEEL
mcp_calculator_financeblue-0.1.0.dist-info/entry_points.txt
mcp_calculator_financeblue-0.1.0.dist-info/top_level.txt
mcp_calculator_financeblue-0.1.0.dist-info/RECORD
